py_api_dumper/__init__.py
py_api_dumper/cli.py
py_api_dumper-3.0.2.dist-info/licenses/LICENSES/MIT.txt
py_api_dumper-3.0.2.dist-info/METADATA
py_api_dumper-3.0.2.dist-info/WHEEL
py_api_dumper-3.0.2.dist-info/entry_points.txt
py_api_dumper-3.0.2.dist-info/top_level.txt
py_api_dumper-3.0.2.dist-info/RECORD
