Metadata-Version: 2.4
Name: py-api-dumper
Version: 3.0.2
Summary: Python API dumping and comparison tool
Author-email: Karl Wette <karl.wette@anu.edu.au>
License-Expression: MIT
Project-URL: Homepage, https://github.com/kwwette/py-api-dumper
Project-URL: Issues, https://github.com/kwwette/py-api-dumper/issues
Classifier: Programming Language :: Python :: 3
Classifier: Operating System :: OS Independent
Requires-Python: >=3.9
License-File: LICENSES/MIT.txt
Dynamic: license-file
